MANIFEST.in
README
setup.py
django_qourisman.egg-info/PKG-INFO
django_qourisman.egg-info/SOURCES.txt
django_qourisman.egg-info/dependency_links.txt
django_qourisman.egg-info/not-zip-safe
django_qourisman.egg-info/top_level.txt
qourisman/__init__.py
qourisman/models.py
qourisman/auth/__init__.py
qourisman/auth/view_permission.py
qourisman/filterspecs/__init__.py
qourisman/filterspecs/null_related.py
qourisman/listfilters/__init__.py
qourisman/listfilters/null_related.py
qourisman/templates/admin/change_form.html
qourisman/templatetags/__init__.py
qourisman/templatetags/admin_modify_view_permission.py