Metadata-Version: 1.0
Name: django-qourisman
Version: 0.0.7
Summary: A collection of Django admin extensions
Home-page: https://github.com/django-district/django-qourisman
Author: UNKNOWN
Author-email: UNKNOWN
License: http://code.djangoproject.com/browser/django/trunk/LICENSE
Platform: UNKNOWN
